MANIFEST.in
README.rst
setup.cfg
setup.py
spark_sklearn/__init__.py
spark_sklearn/base_search.py
spark_sklearn/converter.py
spark_sklearn/converter_test.py
spark_sklearn/grid_search.py
spark_sklearn/group_apply.py
spark_sklearn/keyed_models.py
spark_sklearn/random_search.py
spark_sklearn/test_utils.py
spark_sklearn/udt.py
spark_sklearn/util.py
spark_sklearn.egg-info/PKG-INFO
spark_sklearn.egg-info/SOURCES.txt
spark_sklearn.egg-info/dependency_links.txt
spark_sklearn.egg-info/not-zip-safe
spark_sklearn.egg-info/requires.txt
spark_sklearn.egg-info/top_level.txt