Metadata-Version: 1.2
Name: spark-sklearn
Version: 0.3.0
Summary: Integration tools for running scikit-learn on Spark
Home-page: https://github.com/databricks/spark-sklearn
Author: Joseph Bradley
Author-email: joseph@databricks.com
Maintainer: Tim Hunter
Maintainer-email: timhunter@databricks.com
License: Apache 2.0
Keywords: spark,scikit-learn,distributed computing,machine learning
Platform: UNKNOWN
Classifier: Programming Language :: Python :: 2.6
Classifier: Programming Language :: Python :: 2.7
Classifier: Programming Language :: Python :: 3
Classifier: Programming Language :: Python :: 3.2
Classifier: Development Status :: 4 - Beta
Classifier: Intended Audience :: Developers
Classifier: Natural Language :: English
Classifier: License :: OSI Approved :: Apache Software License
Classifier: Operating System :: OS Independent
Classifier: Programming Language :: Python
Classifier: Topic :: Scientific/Engineering
